<?xml version="1.0" encoding="UTF-8" standalone="yes"?>
<competences xmlns:xsi="http://www.w3.org/2001/XMLSchema-instance">
	<personne trigramme="ALC">
		<gestion_test_en_cycle_en_v>3</gestion_test_en_cycle_en_v>
		<agile>1</agile>
		<pilotage_projet>1</pilotage_projet>
		<certification_istqb>4</certification_istqb>
		<applications_casino>4</applications_casino>
		<squash_tm>4</squash_tm>
		<jira_confluence>3</jira_confluence>
		<gitlab>3</gitlab>
		<mainframe>3</mainframe>
		<scripting_test_automatises>2</scripting_test_automatises>
		<outil_automatisation>0</outil_automatisation>
		<gestion_de_versionning>2</gestion_de_versionning>
		<integration_continue>0</integration_continue>
	</personne>
	<personne trigramme="CBE">
		<gestion_test_en_cycle_en_v>3</gestion_test_en_cycle_en_v>
		<agile>2</agile>
		<pilotage_projet>1</pilotage_projet>
		<certification_istqb>4</certification_istqb>
		<applications_casino>4</applications_casino>
		<squash_tm>4</squash_tm>
		<jira_confluence>1</jira_confluence>
		<gitlab>3</gitlab>
		<mainframe>2</mainframe>
		<scripting_test_automatises>3</scripting_test_automatises>
		<outil_automatisation>1</outil_automatisation>
		<gestion_de_versionning>2</gestion_de_versionning>
		<integration_continue>1</integration_continue>
	</personne>
	<personne trigramme="FBB">
		<gestion_test_en_cycle_en_v>3</gestion_test_en_cycle_en_v>
		<agile>3</agile>
		<pilotage_projet>1</pilotage_projet>
		<certification_istqb>2</certification_istqb>
		<applications_casino>4</applications_casino>
		<squash_tm>3</squash_tm>
		<jira_confluence>2</jira_confluence>
		<gitlab>3</gitlab>
		<mainframe>3</mainframe>
		<scripting_test_automatises>2</scripting_test_automatises>
		<outil_automatisation>0</outil_automatisation>
		<gestion_de_versionning>2</gestion_de_versionning>
		<integration_continue>0</integration_continue>
	</personne>
	<personne trigramme="VAA">
		<gestion_test_en_cycle_en_v>3</gestion_test_en_cycle_en_v>
		<agile>1</agile>
		<pilotage_projet>1</pilotage_projet>
		<certification_istqb>4</certification_istqb>
		<applications_casino>4</applications_casino>
		<squash_tm>4</squash_tm>
		<jira_confluence>3</jira_confluence>
		<gitlab>3</gitlab>
		<mainframe>3</mainframe>
		<scripting_test_automatises>3</scripting_test_automatises>
		<outil_automatisation>3</outil_automatisation>
		<gestion_de_versionning>3</gestion_de_versionning>
		<integration_continue>2</integration_continue>
	</personne>
	<personne trigramme="ABR">
		<gestion_test_en_cycle_en_v>3</gestion_test_en_cycle_en_v>
		<agile>3</agile>
		<pilotage_projet>2</pilotage_projet>
		<certification_istqb>4</certification_istqb>
		<applications_casino>4</applications_casino>
		<squash_tm>4</squash_tm>
		<jira_confluence>3</jira_confluence>
		<gitlab>3</gitlab>
		<mainframe>3</mainframe>
		<scripting_test_automatises>2</scripting_test_automatises>
		<outil_automatisation>1</outil_automatisation>
		<gestion_de_versionning>2</gestion_de_versionning>
		<integration_continue>1</integration_continue>
	</personne>
	<personne trigramme="CDU">
		<gestion_test_en_cycle_en_v>2</gestion_test_en_cycle_en_v>
		<agile>1</agile>
		<pilotage_projet>0</pilotage_projet>
		<certification_istqb>0</certification_istqb>
		<applications_casino>1</applications_casino>
		<squash_tm>1</squash_tm>
		<jira_confluence>4</jira_confluence>
		<gitlab>2</gitlab>
		<mainframe>4</mainframe>
		<scripting_test_automatises>1</scripting_test_automatises>
		<outil_automatisation>0</outil_automatisation>
		<gestion_de_versionning>4</gestion_de_versionning>
		<integration_continue>3</integration_continue>
	</personne>
	<personne trigramme="EBD">
		<gestion_test_en_cycle_en_v>3</gestion_test_en_cycle_en_v>
		<agile>2</agile>
		<pilotage_projet>0</pilotage_projet>
		<certification_istqb>4</certification_istqb>
		<applications_casino>4</applications_casino>
		<squash_tm>3</squash_tm>
		<jira_confluence>3</jira_confluence>
		<gitlab>3</gitlab>
		<mainframe>3</mainframe>
		<scripting_test_automatises>3</scripting_test_automatises>
		<outil_automatisation>2</outil_automatisation>
		<gestion_de_versionning>3</gestion_de_versionning>
		<integration_continue>2</integration_continue>
	</personne>
	<personne trigramme="FPT">
		<gestion_test_en_cycle_en_v>3</gestion_test_en_cycle_en_v>
		<agile>3</agile>
		<pilotage_projet>3</pilotage_projet>
		<certification_istqb>4</certification_istqb>
		<applications_casino>0</applications_casino>
		<squash_tm>3</squash_tm>
		<jira_confluence>2</jira_confluence>
		<gitlab>4</gitlab>
		<mainframe>4</mainframe>
		<scripting_test_automatises>4</scripting_test_automatises>
		<outil_automatisation>4</outil_automatisation>
		<gestion_de_versionning>4</gestion_de_versionning>
		<integration_continue>4</integration_continue>
	</personne>
	<personne trigramme="HHU">
		<gestion_test_en_cycle_en_v>3</gestion_test_en_cycle_en_v>
		<agile>3</agile>
		<pilotage_projet>3</pilotage_projet>
		<certification_istqb>0</certification_istqb>
		<applications_casino>2</applications_casino>
		<squash_tm>2</squash_tm>
		<jira_confluence>3</jira_confluence>
		<gitlab>2</gitlab>
		<mainframe>3</mainframe>
		<scripting_test_automatises>1</scripting_test_automatises>
		<outil_automatisation>0</outil_automatisation>
		<gestion_de_versionning>3</gestion_de_versionning>
		<integration_continue>2</integration_continue>
	</personne>
	<personne trigramme="JBO">
		<gestion_test_en_cycle_en_v>3</gestion_test_en_cycle_en_v>
		<agile>2</agile>
		<pilotage_projet>2</pilotage_projet>
		<certification_istqb>4</certification_istqb>
		<applications_casino>4</applications_casino>
		<squash_tm>3</squash_tm>
		<jira_confluence>3</jira_confluence>
		<gitlab>3</gitlab>
		<mainframe>2</mainframe>
		<scripting_test_automatises>2</scripting_test_automatises>
		<outil_automatisation>1</outil_automatisation>
		<gestion_de_versionning>3</gestion_de_versionning>
		<integration_continue>3</integration_continue>
	</personne>
	<personne trigramme="SLT">
		<gestion_test_en_cycle_en_v>3</gestion_test_en_cycle_en_v>
		<agile>4</agile>
		<pilotage_projet>2</pilotage_projet>
		<certification_istqb>4</certification_istqb>
		<applications_casino>4</applications_casino>
		<squash_tm>4</squash_tm>
		<jira_confluence>3</jira_confluence>
		<gitlab>3</gitlab>
		<mainframe>3</mainframe>
		<scripting_test_automatises>3</scripting_test_automatises>
		<outil_automatisation>3</outil_automatisation>
		<gestion_de_versionning>3</gestion_de_versionning>
		<integration_continue>3</integration_continue>
	</personne>
	<personne trigramme="FMU">
		<gestion_test_en_cycle_en_v>4</gestion_test_en_cycle_en_v>
		<agile>2</agile>
		<pilotage_projet>4</pilotage_projet>
		<certification_istqb>0</certification_istqb>
		<applications_casino>3</applications_casino>
		<squash_tm>3</squash_tm>
		<jira_confluence>1</jira_confluence>
		<gitlab>3</gitlab>
		<mainframe>2</mainframe>
		<scripting_test_automatises>0</scripting_test_automatises>
		<outil_automatisation>0</outil_automatisation>
		<gestion_de_versionning>0</gestion_de_versionning>
		<integration_continue>0</integration_continue>
	</personne>
	<personne trigramme="WEN">
		<gestion_test_en_cycle_en_v>2</gestion_test_en_cycle_en_v>
		<agile>1</agile>
		<pilotage_projet>1</pilotage_projet>
		<certification_istqb>2</certification_istqb>
		<applications_casino>3</applications_casino>
		<squash_tm>3</squash_tm>
		<jira_confluence>2</jira_confluence>
		<gitlab>3</gitlab>
		<mainframe>3</mainframe>
		<scripting_test_automatises>0</scripting_test_automatises>
		<outil_automatisation>0</outil_automatisation>
		<gestion_de_versionning>0</gestion_de_versionning>
		<integration_continue>0</integration_continue>
	</personne>
	<personne trigramme="VDE">
		<gestion_test_en_cycle_en_v>3</gestion_test_en_cycle_en_v>
		<agile>2</agile>
		<pilotage_projet>2</pilotage_projet>
		<certification_istqb>4</certification_istqb>
		<applications_casino>4</applications_casino>
		<squash_tm>3</squash_tm>
		<jira_confluence>2</jira_confluence>
		<gitlab>3</gitlab>
		<mainframe>3</mainframe>
		<scripting_test_automatises>1</scripting_test_automatises>
		<outil_automatisation>0</outil_automatisation>
		<gestion_de_versionning>2</gestion_de_versionning>
		<integration_continue>0</integration_continue>
	</personne>
	<personne trigramme="CCI">
		<gestion_test_en_cycle_en_v>4</gestion_test_en_cycle_en_v>
		<agile>3</agile>
		<pilotage_projet>2</pilotage_projet>
		<certification_istqb>0</certification_istqb>
		<applications_casino>3</applications_casino>
		<squash_tm>3</squash_tm>
		<jira_confluence>1</jira_confluence>
		<gitlab>3</gitlab>
		<mainframe>2</mainframe>
		<scripting_test_automatises>1</scripting_test_automatises>
		<outil_automatisation>0</outil_automatisation>
		<gestion_de_versionning>1</gestion_de_versionning>
		<integration_continue>0</integration_continue>
	</personne>
	<personne trigramme="ADA">
		<gestion_test_en_cycle_en_v>4</gestion_test_en_cycle_en_v>
		<agile>2</agile>
		<pilotage_projet>1</pilotage_projet>
		<certification_istqb>4</certification_istqb>
		<applications_casino>4</applications_casino>
		<squash_tm>4</squash_tm>
		<jira_confluence>2</jira_confluence>
		<gitlab>4</gitlab>
		<mainframe>4</mainframe>
		<scripting_test_automatises>1</scripting_test_automatises>
		<outil_automatisation>0</outil_automatisation>
		<gestion_de_versionning>1</gestion_de_versionning>
		<integration_continue>0</integration_continue>
	</personne>
	<personne trigramme="JGGZ">
		<gestion_test_en_cycle_en_v>3</gestion_test_en_cycle_en_v>
		<agile>3</agile>
		<pilotage_projet>3</pilotage_projet>
		<certification_istqb>4</certification_istqb>
		<applications_casino>0</applications_casino>
		<squash_tm>4</squash_tm>
		<jira_confluence>2</jira_confluence>
		<gitlab>4</gitlab>
		<mainframe>4</mainframe>
		<scripting_test_automatises>4</scripting_test_automatises>
		<outil_automatisation>4</outil_automatisation>
		<gestion_de_versionning>4</gestion_de_versionning>
		<integration_continue>4</integration_continue>
	</personne>
</competences>